distro_prb/Binomialdistribution.py
distro_prb/Gaussiandistribution.py
distro_prb/Generaldistribution.py
distro_prb/__init__.py
distro_prb-0.3.dist-info/DESCRIPTION.rst
distro_prb-0.3.dist-info/METADATA
distro_prb-0.3.dist-info/RECORD
distro_prb-0.3.dist-info/WHEEL
distro_prb-0.3.dist-info/metadata.json
distro_prb-0.3.dist-info/top_level.txt
